{
  "description": "NJY zuoti WeChat mini program",
  "packOptions": {
    "ignore": [],
    "include": []
  },
  "setting": {
    "urlCheck": true,
    "es6": true,
    "enhance": true,
    "postcss": true,
    "minified": true,
    "newFeature": true,
    "babelSetting": {
      "ignore": [],
      "disablePlugins": [],
      "outputPath": ""
    }
  },
  "compileType": "miniprogram",
  "libVersion": "latest",
  "appid": "wxb88840bf78c6cd4d",
  "projectname": "NJY_zuoti_Fe",
  "condition": {},
  "editorSetting": {
    "tabIndent": "insertSpaces",
    "tabSize": 2
  }
}